{
  "rpcUrl": "https://api.mainnet-beta.solana.com",
  "dryRun": true,
  "keypairFilePath": "keypair.json",
  "computeUnitPriceMicroLamports": 100000,
  "baseMint": "3B5wuUrMEi5yATD7on46hKfej3pfmd7t1RKgrsN3pump",
  "quoteSymbol": "SOL",
  "dynamicAmm": {
    "baseAmount": "100",
    "quoteAmount": "0.001",
    "tradeFeeNumerator": 2500,
    "activationType": "timestamp",
    "activationPoint": null,
    "hasAlphaVault": true
  },
  "alphaVault": {
    "poolType": "dynamic",
    "alphaVaultType": "fcfs",
    "depositingPoint": 1733547099,
    "startVestingPoint": 1733548099,
    "endVestingPoint": 1733549099,
    "maxDepositCap": 100,
    "individualDepositingCap": 1,
    "escrowFee": 0,
    "whitelistMode": "permissioned_with_merkle_proof",
    "whitelistFilepath": "./config/whitelist_wallet.csv"
  }
}